re2-stubs/__init__.pyi
re2-stubs/py.typed
google_re2_stubs-0.1.1.dist-info/LICENSE
google_re2_stubs-0.1.1.dist-info/METADATA
google_re2_stubs-0.1.1.dist-info/WHEEL
google_re2_stubs-0.1.1.dist-info/RECORD
