Metadata-Version: 2.1
Name: google-re2-stubs
Version: 0.1.1
Summary: Typestubs for google-re2
License: MIT
Author: Donald Nguyen
Requires-Python: >=3.8.0,<4.0.0
Classifier: License :: OSI Approved :: MIT License
Classifier: Programming Language :: Python :: 3
Classifier: Programming Language :: Python :: 3.8
Classifier: Programming Language :: Python :: 3.9
Classifier: Programming Language :: Python :: 3.10
Classifier: Programming Language :: Python :: 3.11
Classifier: Programming Language :: Python :: 3.12
Classifier: Programming Language :: Python :: 3.13
Requires-Dist: google-re2 (>=1.0)
